poetry_kernel/__init__.py
poetry_kernel/__main__.py
poetry_kernel/kernelspec.py
poetry_kernel-0.1.3.data/data/share/jupyter/kernels/poetry-kernel/kernel.json
poetry_kernel-0.1.3.dist-info/LICENSE.md
poetry_kernel-0.1.3.dist-info/METADATA
poetry_kernel-0.1.3.dist-info/WHEEL
poetry_kernel-0.1.3.dist-info/top_level.txt
poetry_kernel-0.1.3.dist-info/RECORD
