Metadata-Version: 2.1
Name: poetry-kernel
Version: 0.1.3
Summary: Python Jupyter kernel using Poetry for dependency management
Home-page: https://github.com/pathbird/poetry-kernel
Author: Pathbird Inc
Author-email: oss@pathbird.com
License: MIT
Keywords: Interactive,Interpreter,Shell,Web
Platform: UNKNOWN
Classifier: Framework :: Jupyter
Classifier: Intended Audience :: Developers
Classifier: Intended Audience :: System Administrators
Classifier: Intended Audience :: Science/Research
Classifier: License :: OSI Approved :: MIT License
Classifier: Operating System :: OS Independent
Classifier: Programming Language :: Python
Classifier: Programming Language :: Python :: 3
Requires-Python: >=3.7
License-File: LICENSE.md
Requires-Dist: jupyter-client (>=7.0.1)
Requires-Dist: colorama (~=0.4.4)
